col/webapp.py
webapp2PP-1.0.1.dist-info/LICENSE
webapp2PP-1.0.1.dist-info/METADATA
webapp2PP-1.0.1.dist-info/WHEEL
webapp2PP-1.0.1.dist-info/entry_points.txt
webapp2PP-1.0.1.dist-info/top_level.txt
webapp2PP-1.0.1.dist-info/RECORD
